Metadata-Version: 2.4
Name: meu_investimento-package
Version: 1.0.1
Summary: Pacote para calcular o retorno de investimento em ações.
Home-page: https://github.com/aarondmt/meu_investimento
Author: Aaron Lesbão Dumont
Author-email: aarondmt@gmail.com
License: MIT
Classifier: Programming Language :: Python :: 3
Classifier: License :: OSI Approved :: MIT License
Classifier: Operating System :: OS Independent
Requires-Python: >=3.6
Dynamic: author
Dynamic: author-email
Dynamic: classifier
Dynamic: description
Dynamic: description-content-type
Dynamic: home-page
Dynamic: license
Dynamic: requires-python
Dynamic: summary
